displayio_annotation.py
circuitpython_displayio_annotation-3.0.0.dist-info/licenses/LICENSE
circuitpython_displayio_annotation-3.0.0.dist-info/METADATA
circuitpython_displayio_annotation-3.0.0.dist-info/WHEEL
circuitpython_displayio_annotation-3.0.0.dist-info/top_level.txt
circuitpython_displayio_annotation-3.0.0.dist-info/RECORD
