Metadata-Version: 2.4
Name: circuitpython-displayio-annotation
Version: 3.0.0
Summary: A CircuitPython DisplayIO widget for annotating other widgets or freeform positions.
Author: CircuitPython Organization
License: MIT
Project-URL: Homepage, https://github.com/circuitpython/CircuitPython_Org_DisplayIO_Annotation
Keywords: adafruit,blinka,circuitpython,micropython,displayio_annotation,displayio,annotation,graphics,widget
Classifier: Intended Audience :: Developers
Classifier: Topic :: Software Development :: Libraries
Classifier: Topic :: Software Development :: Embedded Systems
Classifier: Topic :: System :: Hardware
Classifier: License :: OSI Approved :: MIT License
Classifier: Programming Language :: Python :: 3
License-File: LICENSE
Requires-Dist: Adafruit-Blinka
Requires-Dist: adafruit-circuitpython-display-text
Requires-Dist: adafruit-circuitpython-display_shapes
Requires-Dist: adafruit-circuitpython-displayio-layout
Provides-Extra: optional
Dynamic: license-file
